jokes_programming/__init__.py
jokes_programming/funny_asks.py
jokes_programming/run.py
jokes_programming-1.0.0.dist-info/METADATA
jokes_programming-1.0.0.dist-info/WHEEL
jokes_programming-1.0.0.dist-info/entry_points.txt
jokes_programming-1.0.0.dist-info/top_level.txt
jokes_programming-1.0.0.dist-info/RECORD
